dec_profiler/__init__.py
dec_profiler/data_templates.py
dec_profiler/README.md
dec_profiler/test/__init__.py
dec_profiler/test/test_time_dec.py
dec_profiler/time_dec.py
dec_profiler-0.1.0.3.dist-info/WHEEL
dec_profiler-0.1.0.3.dist-info/METADATA
dec_profiler-0.1.0.3.dist-info/RECORD
