Metadata-Version: 2.1
Name: dec-profiler
Version: 0.1.0.3
Summary: Тестирование производительности кода
Home-page: https://github.com/denisxab/dec_profiler
License: Apache-2.0
Keywords: profiler
Author: Denis Kustov
Author-email: denis-kustov@rambler.ru
Requires-Python: >=3.5,<4.0
Classifier: License :: OSI Approved :: Apache Software License
Classifier: Programming Language :: Python :: 3
Classifier: Programming Language :: Python :: 3.5
Classifier: Programming Language :: Python :: 3.6
Classifier: Programming Language :: Python :: 3.7
Classifier: Programming Language :: Python :: 3.8
Classifier: Programming Language :: Python :: 3.9
Project-URL: Repository, https://github.com/denisxab/dec_profiler
